ornaments/__init__.py
ornaments/serialize/__init__.py
ornaments/serialize/csv_serializer.py
ornaments/transform/__init__.py
ornaments/transform/strings.py
ornaments/validate/__init__.py
ornaments/validate/length.py
ornaments-0.1.5.dist-info/WHEEL
ornaments-0.1.5.dist-info/METADATA
ornaments-0.1.5.dist-info/RECORD
